factrainer/catboost/__init__.py
factrainer/catboost/py.typed
factrainer/core/__init__.py
factrainer/core/model_container.py
factrainer/core/py.typed
factrainer/core/single.py
factrainer/core/cv/__init__.py
factrainer/core/cv/config.py
factrainer/core/cv/dataset.py
factrainer/core/cv/model_container.py
factrainer/core/cv/raw_model.py
factrainer/lightgbm/__init__.py
factrainer/lightgbm/config.py
factrainer/lightgbm/py.typed
factrainer/lightgbm/raw_model.py
factrainer/lightgbm/dataset/__init__.py
factrainer/lightgbm/dataset/dataset.py
factrainer/lightgbm/dataset/slicer.py
factrainer/lightgbm/dataset/types.py
factrainer/sklearn/__init__.py
factrainer/sklearn/config.py
factrainer/sklearn/py.typed
factrainer/sklearn/raw_model.py
factrainer/sklearn/dataset/__init__.py
factrainer/sklearn/dataset/dataset.py
factrainer/sklearn/dataset/types.py
factrainer/xgboost/__init__.py
factrainer/xgboost/py.typed
factrainer-0.1.27.dist-info/METADATA
factrainer-0.1.27.dist-info/WHEEL
factrainer-0.1.27.dist-info/licenses/LICENSE
factrainer-0.1.27.dist-info/RECORD
