Metadata-Version: 2.4
Name: factrainer
Version: 0.1.27
Summary: Framework Agnostic Cross-validation Trainer
Project-URL: Homepage, https://github.com/ritsuki1227/factrainer/
Project-URL: Documentation, https://ritsuki1227.github.io/factrainer/stable/
Project-URL: Repository, https://github.com/ritsuki1227/factrainer/
Project-URL: Bug Tracker, https://github.com/ritsuki1227/factrainer/issues/
Author-email: ritsuki1227 <ritsuki1227@gmail.com>
License-Expression: MIT
License-File: LICENSE
Classifier: Development Status :: 4 - Beta
Classifier: Intended Audience :: Developers
Classifier: Intended Audience :: Science/Research
Classifier: License :: OSI Approved :: MIT License
Classifier: Natural Language :: English
Classifier: Operating System :: OS Independent
Classifier: Programming Language :: Python :: 3
Classifier: Programming Language :: Python :: 3 :: Only
Classifier: Programming Language :: Python :: 3.12
Classifier: Programming Language :: Python :: 3.13
Classifier: Programming Language :: Python :: 3.14
Classifier: Topic :: Scientific/Engineering :: Artificial Intelligence
Requires-Python: >=3.12
Requires-Dist: factrainer-core
Provides-Extra: all
Requires-Dist: factrainer-catboost; extra == 'all'
Requires-Dist: factrainer-lightgbm; extra == 'all'
Requires-Dist: factrainer-sklearn; extra == 'all'
Requires-Dist: factrainer-xgboost; extra == 'all'
Provides-Extra: catboost
Requires-Dist: factrainer-catboost; extra == 'catboost'
Provides-Extra: lightgbm
Requires-Dist: factrainer-lightgbm; extra == 'lightgbm'
Provides-Extra: sklearn
Requires-Dist: factrainer-sklearn; extra == 'sklearn'
Provides-Extra: xgboost
Requires-Dist: factrainer-xgboost; extra == 'xgboost'
